<?xml version="1.0" encoding="UTF-8"?>
<openerp>
    <data>
        <record model="ir.ui.view" id="view_account_journal_form">
            <field name="name">account.journal.form</field>
            <field name="model">account.journal</field>
            <field name="inherit_id" ref="account.view_account_journal_form"/>
            <field name="arch" type="xml">
                <xpath expr="//field[@name='sequence_id']" position="after">
                    <field name="file_type"/>
                </xpath>
            </field>
        </record>
    </data>
</openerp>
